MANIFEST.in
README
setup.py
Flask_Fleem.egg-info/PKG-INFO
Flask_Fleem.egg-info/SOURCES.txt
Flask_Fleem.egg-info/dependency_links.txt
Flask_Fleem.egg-info/not-zip-safe
Flask_Fleem.egg-info/requires.txt
Flask_Fleem.egg-info/top_level.txt
flask_fleem/__init__.py
flask_fleem/compat.py
flask_fleem/fleem.py
flask_fleem/theme.py
flask_fleem/theme_manager.py
tests/__init__.py
tests/test_fleem.py
tests/morethemes/cool/info.yaml
tests/morethemes/cool/templates/active.html
tests/morethemes/cool/templates/extending.html
tests/morethemes/cool/templates/hello.html
tests/morethemes/cool/templates/static.html
tests/morethemes/cool/templates/theme_layout.html
tests/templates/active.html
tests/templates/hello.html
tests/templates/static.html
tests/templates/static_parent.html
tests/themes/cool/info.yaml
tests/themes/cool/templates/hello.html
tests/themes/identifier/info.yaml
tests/themes/notthis/info.yaml
tests/themes/plain/info.yaml
tests/themes/plain/license.txt
tests/themes/plain/templates/static.html
tests/themes/warm-theme/info.yaml