Metadata-Version: 1.1
Name: Flask-Fleem
Version: 0.0.5
Summary: Theming for Flask applications
Home-page: http://github.com/thrisp/fleem
Author: thrisp/hurrata
Author-email: blueblank@gmail.com
License: MIT
Platform: any
Classifier: Development Status :: 4 - Beta
Classifier: Environment :: Web Environment
Classifier: Intended Audience :: Developers
Classifier: License :: OSI Approved :: MIT License
Classifier: Operating System :: OS Independent
Classifier: Programming Language :: Python
Classifier: Topic :: Internet :: WWW/HTTP :: Dynamic Content
Classifier: Topic :: Software Development :: Libraries :: Python Modules
